setup.py
qiniu_storage/__init__.py
qiniu_storage/storage.py
qiniu_storage.egg-info/PKG-INFO
qiniu_storage.egg-info/SOURCES.txt
qiniu_storage.egg-info/dependency_links.txt
qiniu_storage.egg-info/top_level.txt