Metadata-Version: 1.0
Name: qiniu-storage
Version: 0.1
Summary: Django storage power by qiniu store
Home-page: https://github.com/jeffkit/qiniu-storage
Author: jeff kit
Author-email: bbmyth@gmail.com
License: UNKNOWN
Platform: UNKNOWN
